microsoft_agents_a365/tooling/__init__.py
microsoft_agents_a365/tooling/py.typed
microsoft_agents_a365/tooling/extensions/__init__.py
microsoft_agents_a365/tooling/models/__init__.py
microsoft_agents_a365/tooling/models/chat_history_message.py
microsoft_agents_a365/tooling/models/chat_message_request.py
microsoft_agents_a365/tooling/models/mcp_server_config.py
microsoft_agents_a365/tooling/models/tool_options.py
microsoft_agents_a365/tooling/services/__init__.py
microsoft_agents_a365/tooling/services/mcp_tool_server_configuration_service.py
microsoft_agents_a365/tooling/utils/__init__.py
microsoft_agents_a365/tooling/utils/constants.py
microsoft_agents_a365/tooling/utils/utility.py
microsoft_agents_a365_tooling-0.2.1.dev9.dist-info/METADATA
microsoft_agents_a365_tooling-0.2.1.dev9.dist-info/WHEEL
microsoft_agents_a365_tooling-0.2.1.dev9.dist-info/top_level.txt
microsoft_agents_a365_tooling-0.2.1.dev9.dist-info/RECORD
