Metadata-Version: 2.4
Name: microsoft-agents-a365-tooling
Version: 0.2.1.dev9
Summary: Agent 365 Tooling SDK, providing functionality to work with Agent 365 Tools.
Author-email: Microsoft <support@microsoft.com>
License: MIT
Project-URL: Homepage, https://github.com/microsoft/Agent365-python
Project-URL: Repository, https://github.com/microsoft/Agent365-python
Project-URL: Issues, https://github.com/microsoft/Agent365-python/issues
Project-URL: Documentation, https://github.com/microsoft/Agent365-python/tree/main/libraries/microsoft-agents-a365-tooling
Classifier: Development Status :: 3 - Alpha
Classifier: Intended Audience :: Developers
Classifier: Programming Language :: Python :: 3
Classifier: Programming Language :: Python :: 3.11
Classifier: Programming Language :: Python :: 3.12
Classifier: Operating System :: OS Independent
Classifier: Topic :: Software Development :: Libraries :: Python Modules
Classifier: Topic :: Scientific/Engineering :: Artificial Intelligence
Requires-Python: >=3.11
Requires-Dist: pydantic>=2.0.0
Requires-Dist: typing-extensions>=4.0.0
Requires-Dist: microsoft-agents-hosting-core>=0.4.0
Provides-Extra: dev
Requires-Dist: pytest>=7.0.0; extra == "dev"
Requires-Dist: pytest-asyncio>=0.21.0; extra == "dev"
Requires-Dist: black>=23.0.0; extra == "dev"
Requires-Dist: ruff>=0.1.0; extra == "dev"
Requires-Dist: mypy>=1.0.0; extra == "dev"
